weld_deps/__init__.py
weld_deps/main.py
weld_deps/contrib/__init__.py
weld_deps/contrib/mecha_auto_include.py
weld_deps-0.16.1.dist-info/METADATA
weld_deps-0.16.1.dist-info/WHEEL
weld_deps-0.16.1.dist-info/licenses/LICENSE
weld_deps-0.16.1.dist-info/RECORD
