Metadata-Version: 2.4
Name: weld-deps
Version: 0.16.1
Author: edayot
License-Expression: MIT
License-File: LICENSE
Requires-Python: >=3.14
Requires-Dist: beet>=0.113.0b10
Requires-Dist: requests>=2.31.0
Requires-Dist: semver>=3.0.2
Provides-Extra: smithed
Requires-Dist: bolt>=0.50.0b5; extra == 'smithed'
Requires-Dist: mecha>=0.102.0b2; extra == 'smithed'
Requires-Dist: smithed>=0.16.0; extra == 'smithed'
